fraud_checker/__init__.py
fraud_checker/backend.py
fraud_checker/exceptions.py
fraud_checker/models.py
fraud_checker/py.typed
fraud_checker-0.1.0.dist-info/METADATA
fraud_checker-0.1.0.dist-info/WHEEL
fraud_checker-0.1.0.dist-info/licenses/LICENSE
fraud_checker-0.1.0.dist-info/RECORD
