Metadata-Version: 2.4
Name: fraud_checker
Version: 0.1.0
Summary: A Python client for checking parcel fraud history for Bangladesh.
Project-URL: Homepage, https://github.com/Almas-Ali/fraud_checker
Project-URL: Documentation, https://github.com/Almas-Ali/fraud_checker#readme
Project-URL: Repository, https://github.com/Almas-Ali/fraud_checker
Project-URL: Issues, https://github.com/Almas-Ali/fraud_checker/issues
Author-email: "Md. Almas Ali" <almaspr3@gmail.com>
License: MIT License
License-File: LICENSE
Classifier: Development Status :: 5 - Production/Stable
Classifier: Intended Audience :: Developers
Classifier: License :: OSI Approved :: MIT License
Classifier: Programming Language :: Python :: 3
Classifier: Programming Language :: Python :: 3.10
Classifier: Programming Language :: Python :: 3.11
Classifier: Programming Language :: Python :: 3.12
Classifier: Programming Language :: Python :: 3.13
Classifier: Topic :: Software Development :: Libraries :: Python Modules
Requires-Python: >=3.10
Requires-Dist: attrs==25.1.0
Requires-Dist: httpx==0.28.1
